pachinko/__init__.py
pachinko/_version.py
pachinko/time_period_step_agent.py
pachinko-0.0.1a1.dist-info/METADATA
pachinko-0.0.1a1.dist-info/WHEEL
pachinko-0.0.1a1.dist-info/top_level.txt
pachinko-0.0.1a1.dist-info/RECORD
