Metadata-Version: 2.1
Name: pachinko
Version: 0.0.1a1
Summary: One-shot optimal decision-making agents and algorithms
Home-page: https://github.com/datavaluepeople/pachinko
Author: datavaluepeople
Author-email: opensource@datavaluepeople.com
License: MIT
Platform: UNKNOWN
Requires-Python: >=3.7
Requires-Dist: numpy
Requires-Dist: scipy
Requires-Dist: jupyter
